Metadata-Version: 2.1
Name: pythonfilemover
Version: 0.4.1
Summary: Move files with ease.
Author: Austin Gomez
Author-email: <doawriting@gmail.com>
Keywords: python,move files,modify files,windows,windows 10,windows 11
Classifier: Development Status :: 1 - Planning
Classifier: Intended Audience :: Developers
Classifier: Programming Language :: Python :: 3
Classifier: Operating System :: Microsoft :: Windows
License-File: LICENSE
